retraction_watch_import/__init__.py
retraction_watch_import/importer.py
retraction_watch_import/run_import.py
retraction_watch_import-0.0.4.dist-info/METADATA
retraction_watch_import-0.0.4.dist-info/WHEEL
retraction_watch_import-0.0.4.dist-info/top_level.txt
retraction_watch_import-0.0.4.dist-info/RECORD
