Metadata-Version: 2.1
Name: retraction-watch-import
Version: 0.0.4
Summary: A tool to import Retraction Watch data
Home-page: https://gitlab.com/crossref/labs/retraction-watch-import
Author: Martin Paul Eve
Author-email: meve@crossref.org
Maintainer-email: Martin Paul Eve <meve@crossref.org>
Project-URL: homepage, https://labs.crossref.org
Project-URL: documentation, https://labs.crossref.org
Project-URL: repository, https://gitlab.com/crossref/labs/retraction-watch-import
Project-URL: changelog, https://gitlab.com/crossref/labs/retraction-watch-import/-/blob/main/CHANGELOG.md
Keywords: academic,retractions,data,import,crossref
Classifier: Development Status :: 4 - Beta
Classifier: Programming Language :: Python
Requires-Python: >=3.8
Requires-Dist: boto3
Requires-Dist: claws >=0.0.20
Requires-Dist: longsight >=1.0.13
Requires-Dist: clannotation
Requires-Dist: tenacity ==8.0.1
Requires-Dist: requests
